grubbs/__init__.py
grubbs-0.0.1.dist-info/LICENSE
grubbs-0.0.1.dist-info/METADATA
grubbs-0.0.1.dist-info/WHEEL
grubbs-0.0.1.dist-info/top_level.txt
grubbs-0.0.1.dist-info/RECORD
