Metadata-Version: 2.1
Name: grubbs
Version: 0.0.1
Summary: Implements the Grubbs test for outliers
Home-page: https://dsbowen.gitlab.io/grubbs
Author: Dillon Bowen
Author-email: dsbowen@wharton.upenn.edu
License: UNKNOWN
Platform: UNKNOWN
Classifier: Programming Language :: Python :: 3
Classifier: License :: OSI Approved :: MIT License
Classifier: Operating System :: OS Independent
Requires-Python: >=3.8
Requires-Dist: numpy (>=1.20)
Requires-Dist: scipy
